Metadata-Version: 1.0
Name: termpy
Version: 0.1
Summary: Term manipulation
Home-page: http://github.com/logpy/termpy/
Author: Matthew Rocklin
Author-email: mrocklin@gmail.com
License: BSD
Platform: UNKNOWN
